[
    {
        "Title":"One",
        "Image":"https://github.com/TeaSipp/GroupActivityTracker/raw/main/one.png",
        "Priority":"High",
        "Type":"Anime"
    },
    {
        "Title":"Two",
        "Image":"https://github.com/TeaSipp/GroupActivityTracker/raw/main/two.png",
        "Priority":"High",
        "Type":"Anime"
    },
    {
        "Title":"Three",
        "Image":"https://github.com/TeaSipp/GroupActivityTracker/raw/main/three.png",
        "Priority":"High",
        "Type":"Anime"
    },
    {
        "Title":"Four",
        "Image":".https://github.com/TeaSipp/GroupActivityTracker/raw/main/four.png",
        "Priority":"High",
        "Type":"Anime"
    },
    {
        "Title":"Five",
        "Image":"https://github.com/TeaSipp/GroupActivityTracker/raw/main/five.png",
        "Priority":"High",
        "Type":"Anime"
    }
]
